LICENSE
README.md
setup.cfg
setup.py
stng/__init__.py
stng/__main__.py
stng/dum_scanner.py
stng/iter_funcs.py
stng/search_result.py
stng/stng.py
stng.egg-info/PKG-INFO
stng.egg-info/SOURCES.txt
stng.egg-info/dependency_links.txt
stng.egg-info/entry_points.txt
stng.egg-info/requires.txt
stng.egg-info/top_level.txt