Metadata-Version: 2.1
Name: stng
Version: 0.3.1
Summary: sentence-transformer-based natural-language grep
Home-page: https://github.com/tos-kamiya/stng
Author: Toshihiro Kamiya
Author-email: kamiya@mbj.nifty.com
License: BSD 2-Clause License
Platform: UNKNOWN
Classifier: Programming Language :: Python :: 3.8
Classifier: Programming Language :: Python :: 3.9
Classifier: Programming Language :: Python :: 3.10
Classifier: License :: OSI Approved :: BSD License
Classifier: Operating System :: MacOS :: MacOS X
Classifier: Operating System :: POSIX :: Linux
Classifier: Operating System :: Microsoft :: Windows :: Windows 10
Requires-Python: >=3.8
Provides-Extra: docopt
Provides-Extra: docopt_ng
License-File: LICENSE
